yapc/__init__.py
yapc/__main__.py
yapc/param.py
yapc-0.1.1.dist-info/entry_points.txt
yapc-0.1.1.dist-info/LICENSE.md
yapc-0.1.1.dist-info/WHEEL
yapc-0.1.1.dist-info/METADATA
yapc-0.1.1.dist-info/RECORD
